cielo_connect_api-1.0.3.dist-info/licenses/LICENSE
cieloconnectapi/__init__.py
cieloconnectapi/client.py
cieloconnectapi/const.py
cieloconnectapi/exceptions.py
cieloconnectapi/model.py
cielo_connect_api-1.0.3.dist-info/METADATA
cielo_connect_api-1.0.3.dist-info/WHEEL
cielo_connect_api-1.0.3.dist-info/top_level.txt
cielo_connect_api-1.0.3.dist-info/RECORD
