Metadata-Version: 2.4
Name: cielo-connect-api
Version: 1.0.3
Summary: Python package for Cielo Connect APIs.
Author: Cielo Wigle Inc. and Muhammad Ihsan
License: MIT
Classifier: Programming Language :: Python :: 3
Classifier: License :: OSI Approved :: MIT License
Classifier: Operating System :: OS Independent
Requires-Python: >=3.8
License-File: LICENSE
Dynamic: author
Dynamic: classifier
Dynamic: description
Dynamic: description-content-type
Dynamic: license
Dynamic: license-file
Dynamic: requires-python
Dynamic: summary
